piplsay/__init__.py
piplsay-0.0.1.dist-info/LICENSE.txt
piplsay-0.0.1.dist-info/METADATA
piplsay-0.0.1.dist-info/WHEEL
piplsay-0.0.1.dist-info/top_level.txt
piplsay-0.0.1.dist-info/RECORD
